authventure/__init__.py
authventure/simpler_authenticator.py
authventure/exceptions/__init__.py
authventure/exceptions/invalid_token_exception.py
authventure/tests/__init__.py
authventure/tests/test_simpler_authenticator.py
build/lib/authventure/__init__.py
build/lib/authventure/simpler_authenticator.py
build/lib/authventure/exceptions/__init__.py
build/lib/authventure/exceptions/invalid_token_exception.py
build/lib/authventure/tests/__init__.py
build/lib/authventure/tests/test_simpler_authenticator.py
build/lib/build/lib/authventure/__init__.py
build/lib/build/lib/authventure/simpler_authenticator.py
build/lib/build/lib/authventure/tests/__init__.py
build/lib/build/lib/authventure/tests/test_simpler_authenticator.py
authventure-1.1.1.dist-info/LICENSE
authventure-1.1.1.dist-info/METADATA
authventure-1.1.1.dist-info/WHEEL
authventure-1.1.1.dist-info/top_level.txt
authventure-1.1.1.dist-info/RECORD
