Metadata-Version: 2.1
Name: authventure
Version: 1.1.1
Summary: Library for the simpler user authentication
Home-page: UNKNOWN
Author: Jesus Hernando Sancha
Author-email: jesushs80@gmail.com
License: MIT
Platform: UNKNOWN
Classifier: Programming Language :: Python :: 3
Classifier: License :: OSI Approved :: MIT License
Classifier: Operating System :: OS Independent
Requires-Python: >=3.7
Requires-Dist: attrs (==20.2.0)
Requires-Dist: coverage (==5.3)
Requires-Dist: importlib-metadata (==2.0.0)
Requires-Dist: iniconfig (==1.0.1)
Requires-Dist: more-itertools (==8.5.0)
Requires-Dist: packaging (==20.4)
Requires-Dist: pluggy (==0.13.1)
Requires-Dist: py (==1.9.0)
Requires-Dist: PyJWT (==1.7.1)
Requires-Dist: pyparsing (==2.4.7)
Requires-Dist: pytest (==6.0.1)
Requires-Dist: pytest-cov (==2.10.1)
Requires-Dist: pytest-mock (==3.3.0)
Requires-Dist: six (==1.15.0)
Requires-Dist: toml (==0.10.1)
Requires-Dist: zipp (==3.3.0)
